aspose/__init__.py
aspose/barcode.cpython-310-darwin.so
aspose/barcode.cpython-311-darwin.so
aspose/barcode.cpython-312-darwin.so
aspose/barcode.cpython-313-darwin.so
aspose/barcode.cpython-38-darwin.so
aspose/barcode.cpython-39-darwin.so
aspose/pycore.cpython-310-darwin.so
aspose/pycore.cpython-311-darwin.so
aspose/pycore.cpython-312-darwin.so
aspose/pycore.cpython-313-darwin.so
aspose/pycore.cpython-38-darwin.so
aspose/pycore.cpython-39-darwin.so
aspose/pydrawing.cpython-310-darwin.so
aspose/pydrawing.cpython-311-darwin.so
aspose/pydrawing.cpython-312-darwin.so
aspose/pydrawing.cpython-313-darwin.so
aspose/pydrawing.cpython-38-darwin.so
aspose/pydrawing.cpython-39-darwin.so
aspose/pygc.cpython-310-darwin.so
aspose/pygc.cpython-311-darwin.so
aspose/pygc.cpython-312-darwin.so
aspose/pygc.cpython-313-darwin.so
aspose/pygc.cpython-38-darwin.so
aspose/pygc.cpython-39-darwin.so
aspose/pyreflection.cpython-310-darwin.so
aspose/pyreflection.cpython-311-darwin.so
aspose/pyreflection.cpython-312-darwin.so
aspose/pyreflection.cpython-313-darwin.so
aspose/pyreflection.cpython-38-darwin.so
aspose/pyreflection.cpython-39-darwin.so
aspose/__pyinstaller/__init__.pyi
aspose/__pyinstaller/hook-aspose.py
aspose/assemblies/barcode/Aspose.BarCode.dll
aspose/assemblies/barcode/Microsoft.Win32.SystemEvents.dll
aspose/assemblies/barcode/System.Drawing.Common.dll
aspose/assemblies/barcode/System.Text.Encoding.CodePages.dll
aspose/assemblies/barcode/WrpInterop.Aspose.BarCode.dll
aspose/assemblies/pycore/WrpInterop.Aspose.PyCore.dll
aspose/assemblies/pydrawing/Microsoft.Win32.SystemEvents.dll
aspose/assemblies/pydrawing/System.Drawing.Common.dll
aspose/assemblies/pydrawing/WrpInterop.Aspose.PyDrawing.dll
aspose/assemblies/pygc/Aspose.PyGC.dll
aspose/assemblies/pyreflection/WrpInterop.Aspose.PyReflection.dll
aspose/barcode/__init__.pyi
aspose/barcode/__nuitka/__init__.pyi
aspose/barcode/__nuitka/aspose-barcode.nuitka-package.config.yml
aspose/barcode/__pyinstaller/__init__.pyi
aspose_barcode_for_python_via_net-25.12.dist-info/METADATA
aspose_barcode_for_python_via_net-25.12.dist-info/WHEEL
aspose_barcode_for_python_via_net-25.12.dist-info/entry_points.txt
aspose_barcode_for_python_via_net-25.12.dist-info/top_level.txt
aspose_barcode_for_python_via_net-25.12.dist-info/RECORD
