Metadata-Version: 2.4
Name: aspose-barcode-for-python-via-net
Version: 25.12
Summary: Aspose.BarCode for Python via .NET is a python libray for generation and recognition of barcodes for many popular formats.
Home-page: https://products.aspose.com/barcode/python-net/
Author: Aspose
License: https://company.aspose.com/legal/eula
Project-URL: Homepage, https://products.aspose.com/barcode/python-net/
Project-URL: API Reference, https://docs.aspose.com/barcode/python-net/api-reference/
Project-URL: Blog, https://blog.aspose.com/category/barcode/
Project-URL: Demos, https://products.aspose.app/barcode/family
Project-URL: Documentation, https://docs.aspose.com/barcode/python-net/
Project-URL: Free support, https://forum.aspose.com/c/barcode/13
Project-URL: Temporary License, https://purchase.aspose.com/temporary-license/
Keywords: Aspose.Barcode, barcode, generation, recognition, Alpha-Numeric, AI-8102-Coupon, AustralianPosteParcel, AustraliaPost, Aztec, Codabar, CodablockF, Code11, Code128, Code16K, Code32, Code39Extended, Code39Standard, Code93Extended, Code93Standard, DatabarExpanded, DatabarExpandedStacked, DatabarLimited, DatabarOmniDirectional, DatabarStacked, DatabarStackedOmniDirectional, DatabarTruncated, DataLogic2of5, DataMatrix, DeutschePostIdentcode, DeutschePostLeitcode, DotCode, DutchKIX, EAN13, E
Platform: macos_arm64
Classifier: Development Status :: 5 - Production/Stable
Classifier: Intended Audience :: Developers
Classifier: Intended Audience :: Information Technology
Classifier: License :: Other/Proprietary License
Classifier: Operating System :: Microsoft :: Windows
Classifier: Operating System :: POSIX :: Linux
Classifier: Operating System :: MacOS
Classifier: Programming Language :: Python :: 3 :: Only
Classifier: Programming Language :: Python :: 3.6
Classifier: Programming Language :: Python :: 3.7
Classifier: Programming Language :: Python :: 3.8
Classifier: Programming Language :: Python :: 3.9
Classifier: Programming Language :: Python :: 3.10
Classifier: Programming Language :: Python :: 3.11
Classifier: Programming Language :: Python :: 3.12
Classifier: Programming Language :: Python :: 3.13
Requires-Python: >=3.6,<3.14
Dynamic: author
Dynamic: classifier
Dynamic: description
Dynamic: description-content-type
Dynamic: home-page
Dynamic: keywords
Dynamic: license
Dynamic: platform
Dynamic: project-url
Dynamic: requires-python
Dynamic: summary
